[{"id":1,"rank_min":1,"rank_max":1,"get_silver":1000000,"get_bind_gold":0,"get_gongxun":25000,"get_item_id":"216","get_item_count":"20"},{"id":2,"rank_min":2,"rank_max":2,"get_silver":500000,"get_bind_gold":0,"get_gongxun":12500,"get_item_id":"216","get_item_count":"10"},{"id":3,"rank_min":3,"rank_max":3,"get_silver":250000,"get_bind_gold":0,"get_gongxun":6250,"get_item_id":"216","get_item_count":"5"},{"id":4,"rank_min":4,"rank_max":10,"get_silver":100000,"get_bind_gold":0,"get_gongxun":3000,"get_item_id":"216","get_item_count":"3"},{"id":5,"rank_min":11,"rank_max":999,"get_silver":50000,"get_bind_gold":0,"get_gongxun":1500,"get_item_id":"216","get_item_count":"1"}]